inutils/__init__.py
inutils/perf.py
inutils/timer.py
inutils-0.1.3.dist-info/LICENSE
inutils-0.1.3.dist-info/WHEEL
inutils-0.1.3.dist-info/METADATA
inutils-0.1.3.dist-info/RECORD
