Metadata-Version: 2.1
Name: inutils
Version: 0.1.3
Summary: INternational UTILS - random utilities
License: MIT
Author: Luiz Menezes
Author-email: luiz.menezesf@gmail.com
Requires-Python: >=3.8,<4.0
Classifier: License :: OSI Approved :: MIT License
Classifier: Programming Language :: Python :: 3
Classifier: Programming Language :: Python :: 3.8
